plotspec/__init__.py
plotspec/_recorder.py
plotspec/_reproducer.py
plotspec/_seaborn.py
plotspec/_serializer.py
plotspec/_signatures/__init__.py
plotspec/_signatures/_loader.py
plotspec/_utils/__init__.py
plotspec/_utils/_diff.py
plotspec/_utils/_image_diff.py
plotspec/_utils/_numpy_io.py
plotspec/_utils/_units.py
plotspec/_wrappers/__init__.py
plotspec/_wrappers/_axes.py
plotspec/_wrappers/_figure.py
plotspec/styles/__init__.py
plotspec/styles/_style_applier.py
plotspec/styles/_style_loader.py
plotspec-0.3.3.dist-info/METADATA
plotspec-0.3.3.dist-info/WHEEL
plotspec-0.3.3.dist-info/RECORD
