Metadata-Version: 2.4
Name: plotspec
Version: 0.3.3
Summary: Record and reproduce matplotlib figures
Project-URL: Homepage, https://github.com/ywatanabe1989/plotspec
Project-URL: Documentation, https://github.com/ywatanabe1989/plotspec#readme
Project-URL: Repository, https://github.com/ywatanabe1989/plotspec.git
Project-URL: Issues, https://github.com/ywatanabe1989/plotspec/issues
Author-email: Yusuke Watanabe <ywatanabe@scitex.ai>
License-Expression: MIT
Keywords: matplotlib,plotting,reproducibility,scientific,visualization
Classifier: Development Status :: 3 - Alpha
Classifier: Intended Audience :: Science/Research
Classifier: License :: OSI Approved :: MIT License
Classifier: Operating System :: OS Independent
Classifier: Programming Language :: Python :: 3
Classifier: Programming Language :: Python :: 3.9
Classifier: Programming Language :: Python :: 3.10
Classifier: Programming Language :: Python :: 3.11
Classifier: Programming Language :: Python :: 3.12
Classifier: Topic :: Scientific/Engineering :: Visualization
Requires-Python: >=3.9
Requires-Dist: matplotlib>=3.5.0
Requires-Dist: numpy>=1.20.0
Requires-Dist: ruamel-yaml>=0.17.0
Provides-Extra: all
Requires-Dist: pandas>=1.3.0; extra == 'all'
Requires-Dist: pillow>=9.0.0; extra == 'all'
Requires-Dist: pytest-cov>=4.0.0; extra == 'all'
Requires-Dist: pytest>=7.0.0; extra == 'all'
Requires-Dist: seaborn>=0.12.0; extra == 'all'
Provides-Extra: dev
Requires-Dist: pytest-cov>=4.0.0; extra == 'dev'
Requires-Dist: pytest>=7.0.0; extra == 'dev'
Provides-Extra: imaging
Requires-Dist: pillow>=9.0.0; extra == 'imaging'
Provides-Extra: seaborn
Requires-Dist: pandas>=1.3.0; extra == 'seaborn'
Requires-Dist: seaborn>=0.12.0; extra == 'seaborn'
